[
  {
    "adult": false,
    "backdrop_path": "/vgpUW4kYIgcyPbomOmXgM37yyCB.jpg",
    "created_by": [],
    "episode_run_time": [
      60
    ],
    "first_air_date": "2019-03-23",
    "genres": [
      {
        "id": 18,
        "name": "دراما"
      },
      {
        "id": 10759,
        "name": "حركة ومغامرة"
      },
      {
        "id": 80,
        "name": "جريمة"
      },
      {
        "id": 9648,
        "name": "غموض"
      }
    ],
    "homepage": "http://program.tving.com/ocn/killit/",
    "id": 87185,
    "in_production": false,
    "languages": [
      "ko"
    ],
    "last_air_date": "2019-04-28",
    "last_episode_to_air": {
      "id": 1736704,
      "name": "الحلقة 12",
      "overview": "",
      "vote_average": 9,
      "vote_count": 1,
      "air_date": "2019-04-28",
      "episode_number": 12,
      "episode_type": "finale",
      "production_code": "",
      "runtime": 68,
      "season_number": 1,
      "show_id": 87185,
      "still_path": null
    },
    "name": "킬잇",
    "next_episode_to_air": null,
    "networks": [
      {
        "id": 627,
        "logo_path": "/x1PpeMBZ1bJzitJyPuuUMRN8u2z.png",
        "name": "OCN",
        "origin_country": "KR"
      }
    ],
    "number_of_episodes": 12,
    "number_of_seasons": 1,
    "origin_country": [
      "KR"
    ],
    "original_language": "ko",
    "original_name": "킬잇",
    "overview": "",
    "popularity": 3.7438,
    "poster_path": "/yJz8UDqMSRGhQbw0NnZ5JQ0nsRn.jpg",
    "production_companies": [
      {
        "id": 86418,
        "logo_path": "/vzzqRwqTin3iAAMw2JlrmVPNnPa.png",
        "name": "Studio Dragon",
        "origin_country": "KR"
      },
      {
        "id": 144329,
        "logo_path": "/83KDOfXjQvrCQTqodVauEc5nujJ.png",
        "name": "Binge Works",
        "origin_country": "KR"
      }
    ],
    "production_countries": [
      {
        "iso_3166_1": "KR",
        "name": "South Korea"
      }
    ],
    "seasons": [
      {
        "air_date": "2019-03-23",
        "episode_count": 12,
        "id": 119618,
        "name": "الموسم 1",
        "overview": "",
        "poster_path": "/sc7i9Qu1VKPZHTRKZgbID6s0twT.jpg",
        "season_number": 1,
        "vote_average": 8.7
      }
    ],
    "softcore": false,
    "spoken_languages": [
      {
        "english_name": "Korean",
        "iso_639_1": "ko",
        "name": "한국어/조선말"
      }
    ],
    "status": "Ended",
    "tagline": "",
    "type": "Scripted",
    "vote_average": 7.62,
    "vote_count": 46,
    "translations": {
      "translations": [
        {
          "iso_3166_1": "US",
          "iso_639_1": "en",
          "name": "English",
          "english_name": "English",
          "data": {
            "name": "Kill It",
            "overview": "The story of a veterinarian killer who saves animals and a detective who saves people.",
            "homepage": "",
            "tagline": ""
          }
        },
        {
          "iso_3166_1": "ES",
          "iso_639_1": "es",
          "name": "Español",
          "english_name": "Spanish",
          "data": {
            "name": "Kill It",
            "overview": "Kim Soo Hyun es un asesino a sueldo que puede volver cualquier objeto un arma contra la gente. Con la habilidad de poder evaluar la situación rápidamente, desarolla el plan perfecto para matar e irse. Le cuesta crear relaciones con la gente alrededor suya, pero siempre busca amor.\n\nDo Hyun Jin se graduó en lo más alto de su clase en la academia de policia y trabaja como una detective en Seúl. Tiene buena intuición y cree en sus instintos, pero también tiene que confiar en los datos cientificos para hacer la mejor decisión. Se ve fría por fuera, pero tiene simpatía por el dolor de los demás.",
            "homepage": "",
            "tagline": ""
          }
        },
        {
          "iso_3166_1": "IL",
          "iso_639_1": "he",
          "name": "עִבְרִית",
          "english_name": "Hebrew",
          "data": {
            "name": "תהרוג אותו",
            "overview": "קים סו היון (השחקן ג'אנג קי יונג) הוא מתנקש עילית. הוא הורג את מטרותיו ונעלם. מאפייני זהותו כמו גזע, גיל או שם לא ידוע לאחרים.\n\nאנשים, כנופיות וארגונים מכל רחבי העולם שוכרים את שירותיו. עמוק בתוך מוחו, הוא רוצה לזכות בחיבה מאנשים. עכשיו, על קים סו היון להרוג כדי למצוא את משפחתו.\n\nדו היון ג'ין (השחקנית ננה) סיימה כמצטיינת הכיתה את אוניברסיטת המשטרה. היא בלשית מצוינת אך גם יהירה. היא לבושה בדרך כלל על פי צו האופנה.\n\nדו היון ג'ין נתפשת כקרה, אבל היא מזדהה עם הנמצאים במצבים מכאיבים.\n\nעכשיו, היא רודפת אחר קים היון סו כדי לחשוף תעלומה הקשורה למותו של המאהב שלה.",
            "homepage": "",
            "tagline": ""
          }
        },
        {
          "iso_3166_1": "CN",
          "iso_639_1": "zh",
          "name": "普通话",
          "english_name": "Mandarin",
          "data": {
            "name": "杀之",
            "overview": "该剧是讲述被恶魔遗弃的男人和被恶魔抚养的女人，以及为了复仇而追击两人的委托人的故事。被恶魔遗弃的男人为了寻找家人而成为杀手，被恶魔抚养长大的女人是一个刑警，她为了替死去的恋人复仇而追踪杀手金诗勋。",
            "homepage": "",
            "tagline": ""
          }
        },
        {
          "iso_3166_1": "KR",
          "iso_639_1": "ko",
          "name": "한국어/조선말",
          "english_name": "Korean",
          "data": {
            "name": "",
            "overview": "모든 생명은 소중하다 했다. 하지만 누군가를 죽여야 살아남을 수 있다는 사람이 있다면? 여기, 살아남기 위해 킬러로 키워진 남자, 김수현이 있다. 타겟을 쫓아 돌아온 한국, 수현은 자신의 신분을 감춘 채 수의사로 활동하고, 의문의 연쇄살인을 쫓던 형사 도현진은 우연한 기회로 수현이 사는 건물에 들어와 함께 생활한다. 동물들을 대할 때는 한 없이 따듯한 수현. 하지만 현진은 그에게서 묘한 이중성을 느끼게 되는데...",
            "homepage": "",
            "tagline": ""
          }
        },
        {
          "iso_3166_1": "UA",
          "iso_639_1": "uk",
          "name": "Український",
          "english_name": "Ukrainian",
          "data": {
            "name": "Вбий",
            "overview": "Любитель тварин, професійний ветеринар, про якого ніхто б не міг подумати, що він, Кім Сухьон (Чан Кійон), насправді один з найнебезпечніших чоловіків на планеті. Створивши образ любителя пухнастих, він приховує свою справжню особистість. В кримінальному світі Кім Сухьон має славу майстерного і анонімного вбивці, який ніколи не залишає по собі слідів. Таємничий і загадковий, він, як примара, шепіт самої смерті, найманець, до якого звертаються зі всього світу, щоб владнати проблеми, з якими не в силах впоратися прості люди.\n\nПовна його протилежність - детектив То Хьончжін, (Нана), віддана своїй справі, за крижаним виразом обличчя якої ховається добродушна дівчина. Використовуючи різні прийоми та навички, вона розслідує справу, яка виводить її прямо на Кім Сухьона. Підозрюючи Кім Сухьона в серійних вбивствах, То Хьончжін копає глибше, аж до самого минулого. Але те, що вона знаходить, потрясає її до глибини душі. Тепер, пов’язані самою долею, То Хьончжін та Кім Сухьон змушені розгадати таємниці, що звели їх разом багато років тому.",
            "homepage": "",
            "tagline": ""
          }
        },
        {
          "iso_3166_1": "TW",
          "iso_639_1": "zh",
          "name": "普通话",
          "english_name": "Mandarin",
          "data": {
            "name": "Kill it 雙面殺手",
            "overview": "本劇講述爲了尋找家人而殺人的殺手和爲了揭開戀人死亡之謎而追捕他的刑警。這兩位需要互相較勁的男女，在不得不向對方開槍的命運中，所上演的追擊愛情故事。",
            "homepage": "",
            "tagline": ""
          }
        },
        {
          "iso_3166_1": "VN",
          "iso_639_1": "vi",
          "name": "Tiếng Việt",
          "english_name": "Vietnamese",
          "data": {
            "name": "Truy Sát - Kill It",
            "overview": "Soo Hyun (Jang Ki Yong) được cưu mang và được đào tạo trở thành sát thủ từ khi còn rất nhỏ. Trái tim từ tấm bé đã phải nhuốm màu chết chóc biến anh trở thành một tay giết thuê máu lạnh hoàn hảo. Khi ẩn thân dưới danh phận bác sĩ thú y, Soo Hyun quen biết với Do Hyun Jin (Nana), một nữ hình sự tài giỏi nhưng kiêu ngạo. Khi va chạm vào cuộc sống của nhau, Soo Hyun và Hyun Jin dần thu hút đối phương bởi sức hút kì lạ của định mệnh. Thế nhưng cả hai không hề biết rằng, họ vốn dĩ chính là mối ác duyên nghiệt ngã khi đôi bên đều là mục tiêu truy đuổi của nhau.",
            "homepage": "",
            "tagline": ""
          }
        },
        {
          "iso_3166_1": "RU",
          "iso_639_1": "ru",
          "name": "Pусский",
          "english_name": "Russian",
          "data": {
            "name": "Убить",
            "overview": "Правило №1 «Никогда и никому не раскрывать личность клиента». Правило №2 «Никогда не оставлять свидетелей в живых». Правило №3 «Выжить».\n\nЕго отец заказал его смерть. Он потерял память и какое-то время жил в странном приюте. Это всё, что знает синеглазый парень Ким Су Хён (Чан Ки Ён), воспитанный киллером Павлом во Владивостоке. Спустя 17 лет  в Корее перед смертью Павел отдает Ким Су Хену фото его предполагаемой матери и сестры. И такое же фото он получает от нового заказчика серии убийств, который в качестве оплаты готов раскрыть Ким Су Хену тайну его прошлого. Но кто этот человек? И как связаны между собой эти «заказанные» люди?\n\nСеульский детектив До Хён Джин (Нана) никогда не забывает своего друга под номером 88 из приюта во Владивостоке, которого мечтает снова встретить.",
            "homepage": "",
            "tagline": ""
          }
        },
        {
          "iso_3166_1": "CZ",
          "iso_639_1": "cs",
          "name": "Český",
          "english_name": "Czech",
          "data": {
            "name": "Kill It",
            "overview": "Mladý nájemný vrah, který trpí od dětství ztrátou paměti, dostane zakázku na několik vražd. Jako odměnu za každou odstraněnou oběť dostane informace, které mu snad umožní zjistit, kdo je a odkud pochází. Celou věc mu komplikuje policistka, odhodlaná vyřešit sérii zdánlivě nesouvisejících úmrtí za každou cenu. Oba přitom spojuje mnohem víc, než tuší.",
            "homepage": "",
            "tagline": ""
          }
        },
        {
          "iso_3166_1": "IT",
          "iso_639_1": "it",
          "name": "Italiano",
          "english_name": "Italian",
          "data": {
            "name": "Kill It",
            "overview": "Mostrandosi come un vero amante degli animali ed esperto veterinario, nessuno sospetterebbe che Kim Soo Hyun (Chang Ki Yong) sia in realtà uno degli uomini più letali che ci siano al mondo. Sfruttando la copertura di paladino degli esseri piccoli e pelosi per nascondere la sua vera identità, Kim Soo Hyun si è fatto un nome fra i gradini più infimi della società diventando un emblema di precisione, abilità e, soprattutto, anonimato. Un mistero nel vero senso della parola, costui non è altro che un fantasma, un'ombra, un sussurro letale, assoldato da individui e organizzazioni di tutto il mondo affinché si occupi di problemi che solo lui è in grado di gestire. All'estremo opposto troviamo Do Hyun Jin (Nana), un'investigatrice dedita al lavoro la cui freddezza esteriore nasconde in realtà un animo comprensivo.",
            "homepage": "",
            "tagline": ""
          }
        },
        {
          "iso_3166_1": "FR",
          "iso_639_1": "fr",
          "name": "Français",
          "english_name": "French",
          "data": {
            "name": "Kill it",
            "overview": "L'histoire d'un vétérinaire tueur qui sauve des animaux et d'un détective qui sauve des gens.",
            "homepage": "",
            "tagline": ""
          }
        },
        {
          "iso_3166_1": "JP",
          "iso_639_1": "ja",
          "name": "日本語",
          "english_name": "Japanese",
          "data": {
            "name": "キル・イット～巡り会うふたり～",
            "overview": "",
            "homepage": "",
            "tagline": ""
          }
        },
        {
          "iso_3166_1": "GR",
          "iso_639_1": "el",
          "name": "ελληνικά",
          "english_name": "Greek",
          "data": {
            "name": "Kill It",
            "overview": "Η ιστορία ενός κτηνιάτρου δολοφόνου που σώζει ζώα και ενός ντετέκτιβ που σώζει ανθρώπους.",
            "homepage": "",
            "tagline": ""
          }
        },
        {
          "iso_3166_1": "BR",
          "iso_639_1": "pt",
          "name": "Português",
          "english_name": "Portuguese",
          "data": {
            "name": "Mate-o",
            "overview": "Um grande amante de animais e veterinário competente, ninguém suspeitaria que Kim Soo Hyun é, na verdade, um dos homens mais mortíferos do mundo. Usando seu disfarce como defensor dos insignificantes e peludos para esconder sua verdadeira identidade, Kim Soo Hyun ficou famoso entre os mais necessitados como o epítome de precisão, habilidade e, acima de tudo, anonimato.",
            "homepage": "",
            "tagline": ""
          }
        },
        {
          "iso_3166_1": "NL",
          "iso_639_1": "nl",
          "name": "Nederlands",
          "english_name": "Dutch",
          "data": {
            "name": "Kill It",
            "overview": "Het verhaal van een dierenartsmoordenaar die dieren redt en een detective die mensen redt.",
            "homepage": "",
            "tagline": ""
          }
        },
        {
          "iso_3166_1": "TH",
          "iso_639_1": "th",
          "name": "ภาษาไทย",
          "english_name": "Thai",
          "data": {
            "name": "",
            "overview": "เรื่องราวของเด็กผู้ชายที่ถูกทิ้งให้อยู่กับปีศาจและเด็กผู้หญิงที่ถูกเลี้ยงโดยปีศาจ และลูกค้าที่ตามล่าพวกเขาทั้งสองเพื่อแก้แค้น เด็กผู้ชายคนนั้นเติบโตมาเป็นนักฆ่าที่พยายามตามหาครอบครัว ในขณะที่เด็กผู้หญิงโตมาเป็นตำรวจ เธอตามสืบเรื่องของนักฆ่าคิมซูฮยอนที่ฆ่าคนรักของเธอ",
            "homepage": "",
            "tagline": ""
          }
        },
        {
          "iso_3166_1": "PL",
          "iso_639_1": "pl",
          "name": "Polski",
          "english_name": "Polish",
          "data": {
            "name": "Kill It",
            "overview": "Historia weterynarza-zabójcy, który ratuje zwierzęta i detektywa, który ratuje ludzi.",
            "homepage": "",
            "tagline": ""
          }
        },
        {
          "iso_3166_1": "HK",
          "iso_639_1": "zh",
          "name": "普通话",
          "english_name": "Mandarin",
          "data": {
            "name": "Kill it 雙面殺手",
            "overview": "本劇講述為了尋找家人而殺人的殺手和為了揭開戀人死亡之謎而追捕他的刑警。這兩位需要互相較勁的男女，在不得不向對方開槍的命運中，所上演的追擊愛情故事。",
            "homepage": "",
            "tagline": ""
          }
        }
      ]
    },
    "media_type": "tv",
    "title": "킬잇",
    "title_en": "Kill It",
    "overview_en": "The story of a veterinarian killer who saves animals and a detective who saves people"
  }
]